dataframe_vis_nb/__init__.py
dataframe_vis_nb/__main__.py
dataframe_vis_nb-0.1.0.dist-info/METADATA
dataframe_vis_nb-0.1.0.dist-info/WHEEL
dataframe_vis_nb-0.1.0.dist-info/entry_points.txt
dataframe_vis_nb-0.1.0.dist-info/RECORD
